ors/__init__.py
ors/client.py
ors/endpoints.py
ors/exceptions.py
ors-0.1.9.dist-info/METADATA
ors-0.1.9.dist-info/WHEEL
ors-0.1.9.dist-info/top_level.txt
ors-0.1.9.dist-info/RECORD
