Metadata-Version: 2.1
Name: ors
Version: 0.1.9
Summary: An openrouteservice client
License: MIT License
Requires-Python: >=3.11
Requires-Dist: urllib3 >=2.2.3
